{"type":"Topology","bbox":[16.6973101,40.2944732,17.8004172,40.8030611],"objects":{"limits_P_073_municipalities":{"type":"GeometryCollection","geometries":[{"type":"MultiPolygon","arcs":[[[0,1]]],"properties":{"adm":8,"osm":40451,"name":"Avetrana",".gpkg":"comuni/geopackage/073001_Avetrana_poly.gpkg","istat":"073001",".osm.pbf":"comuni/pbf/073001_Avetrana_poly.osm.pbf"}},{"type":"MultiPolygon","arcs":[[[2,3,4,5,6,7,8]]],"properties":{"adm":8,"osm":40446,"name":"Lizzano",".gpkg":"comuni/geopackage/073011_Lizzano_poly.gpkg","istat":"073011",".osm.pbf":"comuni/pbf/073011_Lizzano_poly.osm.pbf"}},{"type":"MultiPolygon","arcs":[[[9,-2,10,11,12]]],"properties":{"adm":8,"osm":40426,"name":"Manduria",".gpkg":"comuni/geopackage/073012_Manduria_poly.gpkg","istat":"073012",".osm.pbf":"comuni/pbf/073012_Manduria_poly.osm.pbf"}},{"type":"MultiPolygon","arcs":[[[13,11,14,15]]],"properties":{"adm":8,"osm":40422,"name":"Maruggio",".gpkg":"comuni/geopackage/073014_Maruggio_poly.gpkg","istat":"073014",".osm.pbf":"comuni/pbf/073014_Maruggio_poly.osm.pbf"}},{"type":"MultiPolygon","arcs":[[[16,17,18,19,20,21,22]]],"properties":{"adm":8,"osm":40457,"name":"Pulsano",".gpkg":"comuni/geopackage/073022_Pulsano_poly.gpkg","istat":"073022",".osm.pbf":"comuni/pbf/073022_Pulsano_poly.osm.pbf"}},{"type":"MultiPolygon","arcs":[[[23,-16,24,6]],[[25]]],"properties":{"adm":8,"osm":40435,"name":"Torricella",".gpkg":"comuni/geopackage/073028_Torricella_poly.gpkg","istat":"073028",".osm.pbf":"comuni/pbf/073028_Torricella_poly.osm.pbf"}},{"type":"MultiPolygon","arcs":[[[26,27,28,29,30,31,32]]],"properties":{"adm":8,"osm":40561,"name":"Castellaneta",".gpkg":"comuni/geopackage/073003_Castellaneta_poly.gpkg","istat":"073003",".osm.pbf":"comuni/pbf/073003_Castellaneta_poly.osm.pbf"}},{"type":"MultiPolygon","arcs":[[[33,34,35,36,37,38,39,40,41,42,43,44,45,46,47,48]],[[49]],[[50,51,52]]],"properties":{"adm":8,"osm":40537,"name":"Grottaglie",".gpkg":"comuni/geopackage/073008_Grottaglie_poly.gpkg","istat":"073008",".osm.pbf":"comuni/pbf/073008_Grottaglie_poly.osm.pbf"}},{"type":"MultiPolygon","arcs":[[[53,54,55,56,57,58]]],"properties":{"adm":8,"osm":40520,"name":"Roccaforzata",".gpkg":"comuni/geopackage/073023_Roccaforzata_poly.gpkg","istat":"073023",".osm.pbf":"comuni/pbf/073023_Roccaforzata_poly.osm.pbf"}},{"type":"MultiPolygon","arcs":[[[59,-41,60,61,62]]],"properties":{"adm":8,"osm":40521,"name":"San Marzano di San Giuseppe",".gpkg":"comuni/geopackage/073025_San Marzano di San Giuseppe_poly.gpkg","istat":"073025",".osm.pbf":"comuni/pbf/073025_San Marzano di San Giuseppe_poly.osm.pbf"}},{"type":"MultiPolygon","arcs":[[[63,64,-49,65,66]],[[67]],[[68]],[[69]],[[70]],[[71]],[[72,-35]]],"properties":{"adm":8,"osm":40611,"name":"Crispiano",".gpkg":"comuni/geopackage/073004_Crispiano_poly.gpkg","istat":"073004",".osm.pbf":"comuni/pbf/073004_Crispiano_poly.osm.pbf"}},{"type":"MultiPolygon","arcs":[[[73,74,-52,75,-38,76,-36,-73,-34,-65,77]],[[78]],[[79]],[[80]]],"properties":{"adm":8,"osm":40610,"name":"Martina Franca",".gpkg":"comuni/geopackage/073013_Martina Franca_poly.gpkg","istat":"073013",".osm.pbf":"comuni/pbf/073013_Martina Franca_poly.osm.pbf"}},{"type":"MultiPolygon","arcs":[[[81,-66,-48,82]]],"properties":{"adm":8,"osm":40590,"name":"Montemesola",".gpkg":"comuni/geopackage/073017_Montemesola_poly.gpkg","istat":"073017",".osm.pbf":"comuni/pbf/073017_Montemesola_poly.osm.pbf"}},{"type":"MultiPolygon","arcs":[[[83,-45,84,85,86]]],"properties":{"adm":8,"osm":40535,"name":"Carosino",".gpkg":"comuni/geopackage/073002_Carosino_poly.gpkg","istat":"073002",".osm.pbf":"comuni/pbf/073002_Carosino_poly.osm.pbf"}},{"type":"MultiPolygon","arcs":[[[87,-54,88]],[[89,-58,90,-3,91,18,92,20]]],"properties":{"adm":8,"osm":40482,"name":"Faggiano",".gpkg":"comuni/geopackage/073005_Faggiano_poly.gpkg","istat":"073005",".osm.pbf":"comuni/pbf/073005_Faggiano_poly.osm.pbf"}},{"type":"MultiPolygon","arcs":[[[-43,93,-63,94,-5,95]]],"properties":{"adm":8,"osm":40510,"name":"Fragagnano",".gpkg":"comuni/geopackage/073006_Fragagnano_poly.gpkg","istat":"073006",".osm.pbf":"comuni/pbf/073006_Fragagnano_poly.osm.pbf"}},{"type":"MultiPolygon","arcs":[[[96,-32,97]]],"properties":{"adm":8,"osm":40523,"name":"Ginosa",".gpkg":"comuni/geopackage/073007_Ginosa_poly.gpkg","istat":"073007",".osm.pbf":"comuni/pbf/073007_Ginosa_poly.osm.pbf"}},{"type":"MultiPolygon","arcs":[[[96,32,98]]],"properties":{"adm":8,"osm":40625,"name":"Laterza",".gpkg":"comuni/geopackage/073009_Laterza_poly.gpkg","istat":"073009",".osm.pbf":"comuni/pbf/073009_Laterza_poly.osm.pbf"}},{"type":"MultiPolygon","arcs":[[[99,22,100]]],"properties":{"adm":8,"osm":40475,"name":"Leporano",".gpkg":"comuni/geopackage/073010_Leporano_poly.gpkg","istat":"073010",".osm.pbf":"comuni/pbf/073010_Leporano_poly.osm.pbf"}},{"type":"MultiPolygon","arcs":[[[101,102,-78,-64,103,104,105]],[[67]],[[68]],[[69]],[[70]],[[71]]],"properties":{"adm":8,"osm":40571,"name":"Massafra",".gpkg":"comuni/geopackage/073015_Massafra_poly.gpkg","istat":"073015",".osm.pbf":"comuni/pbf/073015_Massafra_poly.osm.pbf"}},{"type":"MultiPolygon","arcs":[[[106,83,45,107]]],"properties":{"adm":8,"osm":40557,"name":"Monteiasi",".gpkg":"comuni/geopackage/073016_Monteiasi_poly.gpkg","istat":"073016",".osm.pbf":"comuni/pbf/073016_Monteiasi_poly.osm.pbf"}},{"type":"MultiPolygon","arcs":[[[108,-86,109,-56]]],"properties":{"adm":8,"osm":40530,"name":"Monteparano",".gpkg":"comuni/geopackage/073018_Monteparano_poly.gpkg","istat":"073018",".osm.pbf":"comuni/pbf/073018_Monteparano_poly.osm.pbf"}},{"type":"MultiPolygon","arcs":[[[27,110,111,102,73,112]]],"properties":{"adm":8,"osm":40626,"name":"Mottola",".gpkg":"comuni/geopackage/073019_Mottola_poly.gpkg","istat":"073019",".osm.pbf":"comuni/pbf/073019_Mottola_poly.osm.pbf"}},{"type":"MultiPolygon","arcs":[[[28,113,-111]]],"properties":{"adm":8,"osm":40624,"name":"Palagianello",".gpkg":"comuni/geopackage/073020_Palagianello_poly.gpkg","istat":"073020",".osm.pbf":"comuni/pbf/073020_Palagianello_poly.osm.pbf"}},{"type":"MultiPolygon","arcs":[[[29,114,101,-112,-114]]],"properties":{"adm":8,"osm":40563,"name":"Palagiano",".gpkg":"comuni/geopackage/073021_Palagiano_poly.gpkg","istat":"073021",".osm.pbf":"comuni/pbf/073021_Palagiano_poly.osm.pbf"}},{"type":"MultiPolygon","arcs":[[[87,54,108,86,-107,115]]],"properties":{"adm":8,"osm":40526,"name":"San Giorgio Ionico",".gpkg":"comuni/geopackage/073024_San Giorgio Ionico_poly.gpkg","istat":"073024",".osm.pbf":"comuni/pbf/073024_San Giorgio Ionico_poly.osm.pbf"}},{"type":"MultiPolygon","arcs":[[[5,-25,-15,12,116,61,94]]],"properties":{"adm":8,"osm":40463,"name":"Sava",".gpkg":"comuni/geopackage/073026_Sava_poly.gpkg","istat":"073026",".osm.pbf":"comuni/pbf/073026_Sava_poly.osm.pbf"}},{"type":"MultiPolygon","arcs":[[[117,99,-22,89,58,88,-116,-108,46,82,118,104]],[[119]],[[120]],[[-20,92]],[[49]],[[-18,121,8,91]],[[90,3,95,43,84,109,56]],[[36,76]],[[38,122,50,75]],[[93,59,41]]],"properties":{"adm":8,"osm":40452,"name":"Taranto",".gpkg":"comuni/geopackage/073027_Taranto_poly.gpkg","istat":"073027",".osm.pbf":"comuni/pbf/073027_Taranto_poly.osm.pbf"}},{"type":"MultiPolygon","arcs":[[[-119,81,66,103]]],"properties":{"adm":8,"osm":40591,"name":"Statte",".gpkg":"comuni/geopackage/073029_Statte_poly.gpkg","istat":"073029",".osm.pbf":"comuni/pbf/073029_Statte_poly.osm.pbf"}}]}},"arcs":[[[17.7278791,40.3912246],[17.7679871,40.3115058]],[[17.7679871,40.3115058],[17.7278791,40.3912246]],[[17.4091149,40.382073],[17.4091604,40.3827068]],[[17.4091604,40.3827068],[17.4561563,40.4200758]],[[17.4561563,40.4200758],[17.4847374,40.3976274]],[[17.4847374,40.3976274],[17.491449,40.3869388]],[[17.491449,40.3869388],[17.4690076,40.3146874]],[[17.4690076,40.3146874],[17.4318983,40.3315292]],[[17.4318983,40.3315292],[17.4091149,40.382073]],[[17.546157,40.4385926],[17.7278791,40.3912246]],[[17.7679871,40.3115058],[17.6107264,40.3005484]],[[17.6107264,40.3005484],[17.5608731,40.3534178]],[[17.5608731,40.3534178],[17.546157,40.4385926]],[[17.5038759,40.3011061],[17.6107264,40.3005484]],[[17.5608731,40.3534178],[17.5394661,40.3569814]],[[17.5394661,40.3569814],[17.5038759,40.3011061]],[[17.3402833,40.3621838],[17.3865594,40.3372081]],[[17.3865594,40.3372081],[17.3824513,40.3796137]],[[17.3824513,40.3796137],[17.3688074,40.3961527]],[[17.3688074,40.3961527],[17.3543039,40.3964173]],[[17.3543039,40.3964173],[17.3536084,40.4038158]],[[17.3536084,40.4038158],[17.3433741,40.3902925]],[[17.3433741,40.3902925],[17.3402833,40.3621838]],[[17.4690076,40.3146874],[17.5038759,40.3011061]],[[17.5394661,40.3569814],[17.491449,40.3869388]],[[17.4992678,40.3027768],[17.4992678,40.3027768]],[[16.81469,40.6941112],[16.9315236,40.7138382]],[[16.9315236,40.7138382],[16.9442735,40.630965]],[[16.9442735,40.630965],[16.9580922,40.504088]],[[16.9580922,40.504088],[16.9950717,40.4947231]],[[16.9950717,40.4947231],[16.9106489,40.4420382]],[[16.9106489,40.4420382],[16.8274586,40.5745999]],[[16.8274586,40.5745999],[16.81469,40.6941112]],[[17.3220188,40.6070028],[17.3240977,40.6071566]],[[17.3240977,40.6071566],[17.4108005,40.5991116]],[[17.4108005,40.5991116],[17.4143568,40.5914557]],[[17.4143568,40.5914557],[17.4276428,40.5812363]],[[17.4276428,40.5812363],[17.431845,40.5795923]],[[17.431845,40.5795923],[17.4520509,40.5652173]],[[17.4520509,40.5652173],[17.4872251,40.481905]],[[17.4872251,40.481905],[17.4725378,40.464984]],[[17.4725378,40.464984],[17.4591126,40.4611804]],[[17.4591126,40.4611804],[17.4513152,40.4606947]],[[17.4513152,40.4606947],[17.4264716,40.4764339]],[[17.4264716,40.4764339],[17.4088776,40.4924182]],[[17.4088776,40.4924182],[17.353843,40.5132436]],[[17.353843,40.5132436],[17.3557734,40.5584536]],[[17.3557734,40.5584536],[17.3276142,40.5920422]],[[17.3276142,40.5920422],[17.3220188,40.6070028]],[[17.3558648,40.5215716],[17.3558648,40.5215716]],[[17.4528941,40.5676432],[17.4534875,40.5815608]],[[17.4534875,40.5815608],[17.4572506,40.5810136]],[[17.4572506,40.5810136],[17.4528941,40.5676432]],[[17.3687251,40.4276458],[17.3757425,40.4385845]],[[17.3757425,40.4385845],[17.3996937,40.4562105]],[[17.3996937,40.4562105],[17.4256548,40.4459563]],[[17.4256548,40.4459563],[17.3889576,40.4312955]],[[17.3889576,40.4312955],[17.3694109,40.4267791]],[[17.3694109,40.4267791],[17.3687251,40.4276458]],[[17.4708784,40.4565285],[17.4725378,40.464984]],[[17.4872251,40.481905],[17.543119,40.4406357]],[[17.543119,40.4406357],[17.5067564,40.4293309]],[[17.5067564,40.4293309],[17.4708784,40.4565285]],[[17.155614,40.5716453],[17.1850012,40.6537544]],[[17.1850012,40.6537544],[17.3220188,40.6070028]],[[17.3276142,40.5920422],[17.3150432,40.5505093]],[[17.3150432,40.5505093],[17.155614,40.5716453]],[[17.1617996,40.6169704],[17.1617996,40.6169704]],[[17.1660983,40.6148731],[17.1660983,40.6148731]],[[17.1679441,40.6275583],[17.1679441,40.6275583]],[[17.1688965,40.6161353],[17.1688965,40.6161353]],[[17.1754406,40.6275585],[17.1754406,40.6275585]],[[17.3240977,40.6071566],[17.4108005,40.5991116]],[[17.1773487,40.6852343],[17.2040997,40.7609462]],[[17.2040997,40.7609462],[17.4572506,40.5810136]],[[17.4534875,40.5815608],[17.431845,40.5795923]],[[17.4276428,40.5812363],[17.4143568,40.5914557]],[[17.1850012,40.6537544],[17.1773487,40.6852343]],[[17.2813385,40.7813076],[17.2813385,40.7813076]],[[17.2905128,40.7910331],[17.2905128,40.7910331]],[[17.300129,40.7877689],[17.300129,40.7877689]],[[17.3138413,40.5353064],[17.3150432,40.5505093]],[[17.3557734,40.5584536],[17.3138413,40.5353064]],[[17.3921123,40.4840151],[17.4088776,40.4924182]],[[17.4264716,40.4764339],[17.4309646,40.4539573]],[[17.4309646,40.4539573],[17.399731,40.4587948]],[[17.399731,40.4587948],[17.3921123,40.4840151]],[[17.343483,40.447921],[17.3757425,40.4385845]],[[17.3687251,40.4276458],[17.343483,40.447921]],[[17.3536084,40.4038158],[17.3694109,40.4267791]],[[17.3889576,40.4312955],[17.4091604,40.3827068]],[[17.4091149,40.382073],[17.3824513,40.3796137]],[[17.3688074,40.3961527],[17.3543039,40.3964173]],[[17.4591126,40.4611804],[17.4708784,40.4565285]],[[17.5067564,40.4293309],[17.4847374,40.3976274]],[[17.4561563,40.4200758],[17.4513152,40.4606947]],[[16.7290836,40.6024106],[16.8274586,40.5745999]],[[16.9106489,40.4420382],[16.7290836,40.6024106]],[[16.81469,40.6941112],[16.7290836,40.6024106]],[[17.2846507,40.3797956],[17.3433741,40.3902925]],[[17.3402833,40.3621838],[17.2846507,40.3797956]],[[17.062281,40.5162128],[17.0702438,40.6037361]],[[17.0702438,40.6037361],[17.1773487,40.6852343]],[[17.155614,40.5716453],[17.1410266,40.552844]],[[17.1410266,40.552844],[17.1276073,40.5176135]],[[17.1276073,40.5176135],[17.062281,40.5162128]],[[17.3511216,40.495063],[17.3921123,40.4840151]],[[17.353843,40.5132436],[17.3511216,40.495063]],[[17.3996937,40.4562105],[17.399731,40.4587948]],[[17.4309646,40.4539573],[17.4256548,40.4459563]],[[16.9442735,40.630965],[16.9884225,40.6046915]],[[16.9884225,40.6046915],[17.0702438,40.6037361]],[[17.2040997,40.7609462],[16.9315236,40.7138382]],[[16.9580922,40.504088],[16.9884225,40.6046915]],[[16.9950717,40.4947231],[17.062281,40.5162128]],[[17.3511216,40.495063],[17.343483,40.447921]],[[17.546157,40.4385926],[17.543119,40.4406357]],[[17.1276073,40.5176135],[17.2846507,40.3797956]],[[17.3138413,40.5353064],[17.1410266,40.552844]],[[17.1546995,40.4449737],[17.1546995,40.4449737]],[[17.1792187,40.4368696],[17.1792187,40.4368696]],[[17.3865594,40.3372081],[17.4318983,40.3315292]],[[17.4520509,40.5652173],[17.4528941,40.5676432]]]}
