{"type":"Topology","objects":{"limits_P_033_municipalities":{"type":"GeometryCollection","geometries":[{"properties":{"adm":8,"osm":43864,"name":"Podenzano",".gpkg":"comuni/geopackage/033035_Podenzano_poly.gpkg","istat":"033035",".osm.pbf":"comuni/pbf/033035_Podenzano_poly.osm.pbf"}},{"properties":{"adm":8,"osm":44102,"name":"Monticelli d'Ongina",".gpkg":"comuni/geopackage/033027_Monticelli d'Ongina_poly.gpkg","istat":"033027",".osm.pbf":"comuni/pbf/033027_Monticelli d'Ongina_poly.osm.pbf"}},{"properties":{"adm":8,"osm":43772,"name":"Piozzano",".gpkg":"comuni/geopackage/033034_Piozzano_poly.gpkg","istat":"033034",".osm.pbf":"comuni/pbf/033034_Piozzano_poly.osm.pbf"}},{"properties":{"adm":8,"osm":43981,"name":"Piacenza",".gpkg":"comuni/geopackage/033032_Piacenza_poly.gpkg","istat":"033032",".osm.pbf":"comuni/pbf/033032_Piacenza_poly.osm.pbf"}},{"properties":{"adm":8,"osm":43603,"name":"Gropparello",".gpkg":"comuni/geopackage/033025_Gropparello_poly.gpkg","istat":"033025",".osm.pbf":"comuni/pbf/033025_Gropparello_poly.osm.pbf"}},{"properties":{"adm":8,"osm":44034,"name":"San Pietro in Cerro",".gpkg":"comuni/geopackage/033041_San Pietro in Cerro_poly.gpkg","istat":"033041",".osm.pbf":"comuni/pbf/033041_San Pietro in Cerro_poly.osm.pbf"}},{"properties":{"adm":8,"osm":43618,"name":"Lugagnano Val D'Arda",".gpkg":"comuni/geopackage/033026_Lugagnano Val D'Arda_poly.gpkg","istat":"033026",".osm.pbf":"comuni/pbf/033026_Lugagnano Val D'Arda_poly.osm.pbf"}},{"properties":{"adm":8,"osm":43869,"name":"Besenzone",".gpkg":"comuni/geopackage/033003_Besenzone_poly.gpkg","istat":"033003",".osm.pbf":"comuni/pbf/033003_Besenzone_poly.osm.pbf"}},{"properties":{"adm":8,"osm":43905,"name":"Gossolengo",".gpkg":"comuni/geopackage/033023_Gossolengo_poly.gpkg","istat":"033023",".osm.pbf":"comuni/pbf/033023_Gossolengo_poly.osm.pbf"}},{"properties":{"adm":8,"osm":43474,"name":"Morfasso",".gpkg":"comuni/geopackage/033028_Morfasso_poly.gpkg","istat":"033028",".osm.pbf":"comuni/pbf/033028_Morfasso_poly.osm.pbf"}},{"properties":{"adm":8,"osm":44021,"name":"Castel San Giovanni",".gpkg":"comuni/geopackage/033013_Castel San Giovanni_poly.gpkg","istat":"033013",".osm.pbf":"comuni/pbf/033013_Castel San Giovanni_poly.osm.pbf"}},{"properties":{"adm":8,"osm":43717,"name":"Alseno",".gpkg":"comuni/geopackage/033002_Alseno_poly.gpkg","istat":"033002",".osm.pbf":"comuni/pbf/033002_Alseno_poly.osm.pbf"}},{"properties":{"adm":8,"osm":43891,"name":"Agazzano",".gpkg":"comuni/geopackage/033001_Agazzano_poly.gpkg","istat":"033001",".osm.pbf":"comuni/pbf/033001_Agazzano_poly.osm.pbf"}},{"properties":{"adm":8,"osm":43938,"name":"Cortemaggiore",".gpkg":"comuni/geopackage/033018_Cortemaggiore_poly.gpkg","istat":"033018",".osm.pbf":"comuni/pbf/033018_Cortemaggiore_poly.osm.pbf"}},{"properties":{"adm":8,"osm":43487,"name":"Corte Brugnatella",".gpkg":"comuni/geopackage/033017_Corte Brugnatella_poly.gpkg","istat":"033017",".osm.pbf":"comuni/pbf/033017_Corte Brugnatella_poly.osm.pbf"}},{"properties":{"adm":8,"osm":43904,"name":"Borgonovo Val Tidone",".gpkg":"comuni/geopackage/033006_Borgonovo Val Tidone_poly.gpkg","istat":"033006",".osm.pbf":"comuni/pbf/033006_Borgonovo Val Tidone_poly.osm.pbf"}},{"properties":{"adm":8,"osm":43453,"name":"Zerba",".gpkg":"comuni/geopackage/033047_Zerba_poly.gpkg","istat":"033047",".osm.pbf":"comuni/pbf/033047_Zerba_poly.osm.pbf"}},{"properties":{"adm":8,"osm":43895,"name":"Pontenure",".gpkg":"comuni/geopackage/033037_Pontenure_poly.gpkg","istat":"033037",".osm.pbf":"comuni/pbf/033037_Pontenure_poly.osm.pbf"}},{"properties":{"adm":8,"osm":43361,"name":"Ottone",".gpkg":"comuni/geopackage/033030_Ottone_poly.gpkg","istat":"033030",".osm.pbf":"comuni/pbf/033030_Ottone_poly.osm.pbf"}},{"properties":{"adm":8,"osm":44085,"name":"Sarmato",".gpkg":"comuni/geopackage/033042_Sarmato_poly.gpkg","istat":"033042",".osm.pbf":"comuni/pbf/033042_Sarmato_poly.osm.pbf"}},{"properties":{"adm":8,"osm":43792,"name":"Fiorenzuola d'Arda",".gpkg":"comuni/geopackage/033021_Fiorenzuola d'Arda_poly.gpkg","istat":"033021",".osm.pbf":"comuni/pbf/033021_Fiorenzuola d'Arda_poly.osm.pbf"}},{"properties":{"adm":8,"osm":43739,"name":"Castell'Arquato",".gpkg":"comuni/geopackage/033012_Castell'Arquato_poly.gpkg","istat":"033012",".osm.pbf":"comuni/pbf/033012_Castell'Arquato_poly.osm.pbf"}},{"properties":{"adm":8,"osm":43973,"name":"Villanova sull'Arda",".gpkg":"comuni/geopackage/033046_Villanova sull'Arda_poly.gpkg","istat":"033046",".osm.pbf":"comuni/pbf/033046_Villanova sull'Arda_poly.osm.pbf"}},{"properties":{"adm":8,"osm":43560,"name":"Bobbio",".gpkg":"comuni/geopackage/033005_Bobbio_poly.gpkg","istat":"033005",".osm.pbf":"comuni/pbf/033005_Bobbio_poly.osm.pbf"}},{"properties":{"adm":8,"osm":44124,"name":"Castelvetro Piacentino",".gpkg":"comuni/geopackage/033014_Castelvetro Piacentino_poly.gpkg","istat":"033014",".osm.pbf":"comuni/pbf/033014_Castelvetro Piacentino_poly.osm.pbf"}},{"properties":{"adm":8,"osm":7859108,"name":"Alta Val Tidone",".gpkg":"comuni/geopackage/033049_Alta Val Tidone_poly.gpkg","istat":"033049",".osm.pbf":"comuni/pbf/033049_Alta Val Tidone_poly.osm.pbf"}},{"properties":{"adm":8,"osm":43813,"name":"Rivergaro",".gpkg":"comuni/geopackage/033038_Rivergaro_poly.gpkg","istat":"033038",".osm.pbf":"comuni/pbf/033038_Rivergaro_poly.osm.pbf"}},{"properties":{"adm":8,"osm":43331,"name":"Ferriere",".gpkg":"comuni/geopackage/033020_Ferriere_poly.gpkg","istat":"033020",".osm.pbf":"comuni/pbf/033020_Ferriere_poly.osm.pbf"}},{"properties":{"adm":8,"osm":43583,"name":"Vernasca",".gpkg":"comuni/geopackage/033044_Vernasca_poly.gpkg","istat":"033044",".osm.pbf":"comuni/pbf/033044_Vernasca_poly.osm.pbf"}},{"properties":{"adm":8,"osm":44060,"name":"Rottofreno",".gpkg":"comuni/geopackage/033039_Rottofreno_poly.gpkg","istat":"033039",".osm.pbf":"comuni/pbf/033039_Rottofreno_poly.osm.pbf"}},{"properties":{"adm":8,"osm":43896,"name":"Cadeo",".gpkg":"comuni/geopackage/033007_Cadeo_poly.gpkg","istat":"033007",".osm.pbf":"comuni/pbf/033007_Cadeo_poly.osm.pbf"}},{"properties":{"adm":8,"osm":43698,"name":"Ponte dell'Olio",".gpkg":"comuni/geopackage/033036_Ponte dell'Olio_poly.gpkg","istat":"033036",".osm.pbf":"comuni/pbf/033036_Ponte dell'Olio_poly.osm.pbf"}},{"properties":{"adm":8,"osm":43556,"name":"Bettola",".gpkg":"comuni/geopackage/033004_Bettola_poly.gpkg","istat":"033004",".osm.pbf":"comuni/pbf/033004_Bettola_poly.osm.pbf"}},{"properties":{"adm":8,"osm":44153,"name":"Calendasco",".gpkg":"comuni/geopackage/033008_Calendasco_poly.gpkg","istat":"033008",".osm.pbf":"comuni/pbf/033008_Calendasco_poly.osm.pbf"}},{"properties":{"adm":8,"osm":43750,"name":"Carpaneto Piacentino",".gpkg":"comuni/geopackage/033011_Carpaneto Piacentino_poly.gpkg","istat":"033011",".osm.pbf":"comuni/pbf/033011_Carpaneto Piacentino_poly.osm.pbf"}},{"properties":{"adm":8,"osm":43704,"name":"Vigolzone",".gpkg":"comuni/geopackage/033045_Vigolzone_poly.gpkg","istat":"033045",".osm.pbf":"comuni/pbf/033045_Vigolzone_poly.osm.pbf"}},{"properties":{"adm":8,"osm":43675,"name":"Travo",".gpkg":"comuni/geopackage/033043_Travo_poly.gpkg","istat":"033043",".osm.pbf":"comuni/pbf/033043_Travo_poly.osm.pbf"}},{"properties":{"adm":8,"osm":43907,"name":"Ziano Piacentino",".gpkg":"comuni/geopackage/033048_Ziano Piacentino_poly.gpkg","istat":"033048",".osm.pbf":"comuni/pbf/033048_Ziano Piacentino_poly.osm.pbf"}},{"properties":{"adm":8,"osm":43488,"name":"Coli",".gpkg":"comuni/geopackage/033016_Coli_poly.gpkg","istat":"033016",".osm.pbf":"comuni/pbf/033016_Coli_poly.osm.pbf"}},{"properties":{"adm":8,"osm":43810,"name":"Pianello Val Tidone",".gpkg":"comuni/geopackage/033033_Pianello Val Tidone_poly.gpkg","istat":"033033",".osm.pbf":"comuni/pbf/033033_Pianello Val Tidone_poly.osm.pbf"}},{"properties":{"adm":8,"osm":43946,"name":"Gragnano Trebbiense",".gpkg":"comuni/geopackage/033024_Gragnano Trebbiense_poly.gpkg","istat":"033024",".osm.pbf":"comuni/pbf/033024_Gragnano Trebbiense_poly.osm.pbf"}},{"properties":{"adm":8,"osm":43815,"name":"Gazzola",".gpkg":"comuni/geopackage/033022_Gazzola_poly.gpkg","istat":"033022",".osm.pbf":"comuni/pbf/033022_Gazzola_poly.osm.pbf"}},{"properties":{"adm":8,"osm":43445,"name":"Cerignale",".gpkg":"comuni/geopackage/033015_Cerignale_poly.gpkg","istat":"033015",".osm.pbf":"comuni/pbf/033015_Cerignale_poly.osm.pbf"}},{"properties":{"adm":8,"osm":44042,"name":"Caorso",".gpkg":"comuni/geopackage/033010_Caorso_poly.gpkg","istat":"033010",".osm.pbf":"comuni/pbf/033010_Caorso_poly.osm.pbf"}},{"properties":{"adm":8,"osm":43757,"name":"San Giorgio Piacentino",".gpkg":"comuni/geopackage/033040_San Giorgio Piacentino_poly.gpkg","istat":"033040",".osm.pbf":"comuni/pbf/033040_San Giorgio Piacentino_poly.osm.pbf"}},{"properties":{"adm":8,"osm":43473,"name":"Farini",".gpkg":"comuni/geopackage/033019_Farini_poly.gpkg","istat":"033019",".osm.pbf":"comuni/pbf/033019_Farini_poly.osm.pbf"}}]}},"arcs":[]}
